{
 "generated": "2026-07-24T11:13:42.963Z",
 "nyiso": {
  "nycLoadMw": 5794.716,
  "isoLoadMw": 15876.4511,
  "asOf": "2026-07-24T11:00:00.000Z",
  "fuelMix": [
   {
    "fuel": "Dual Fuel",
    "mw": 3919
   },
   {
    "fuel": "Natural Gas",
    "mw": 2958
   },
   {
    "fuel": "Nuclear",
    "mw": 3243
   },
   {
    "fuel": "Other Fossil Fuels",
    "mw": 0
   },
   {
    "fuel": "Other Renewables",
    "mw": 342
   },
   {
    "fuel": "Wind",
    "mw": 249
   },
   {
    "fuel": "Hydro",
    "mw": 2401
   }
  ],
  "fuelAsOf": "2026-07-24T10:55:00.000Z",
  "nycPriceMwh": 52.82,
  "priceAsOf": "2026-07-24T11:10:00.000Z"
 },
 "buoy": {
  "waveHeightM": 0.8,
  "domPeriodS": 7,
  "waterTempC": 23.2,
  "windMs": 2,
  "airTempC": 21.8,
  "pressureHpa": 1023.6,
  "asOf": "2026-07-24T10:20:00.000Z"
 },
 "subway": {
  "trains": 685,
  "feedsOk": 8,
  "feeds": 8,
  "alerts": 9,
  "asOf": "2026-07-24T11:13:44.645Z"
 },
 "rail": {
  "lirr": {
   "trains": 76,
   "viaVehicles": true
  },
  "mnr": {
   "trains": 264,
   "viaVehicles": true
  },
  "asOf": "2026-07-24T11:13:44.870Z"
 },
 "ferry": {
  "vessels": 24,
  "positions": [
   {
    "lat": 40.68468,
    "lon": -74.01398,
    "label": "H200"
   },
   {
    "lat": 40.70675,
    "lon": -73.98606,
    "label": "H201"
   },
   {
    "lat": 40.73284,
    "lon": -73.96587,
    "label": "H103"
   },
   {
    "lat": 40.74274,
    "lon": -73.97124,
    "label": "H104"
   },
   {
    "lat": 40.68657,
    "lon": -74.0145,
    "label": "H106"
   },
   {
    "lat": 40.72095,
    "lon": -73.96517,
    "label": "H107"
   },
   {
    "lat": 40.58414,
    "lon": -73.83186,
    "label": "H108"
   },
   {
    "lat": 40.74439,
    "lon": -73.97035,
    "label": "H109"
   },
   {
    "lat": 40.71461,
    "lon": -74.01778,
    "label": "H204"
   },
   {
    "lat": 40.69957,
    "lon": -74.02925,
    "label": "H206"
   },
   {
    "lat": 40.70303,
    "lon": -74.00657,
    "label": "H208"
   },
   {
    "lat": 40.59494,
    "lon": -73.76967,
    "label": "SB402"
   },
   {
    "lat": 40.5824,
    "lon": -73.83018,
    "label": "SB406"
   },
   {
    "lat": 40.61047,
    "lon": -74.04224,
    "label": "H111"
   },
   {
    "lat": 40.74369,
    "lon": -73.97034,
    "label": "H113"
   },
   {
    "lat": 40.5839,
    "lon": -73.8315,
    "label": "SBC409"
   },
   {
    "lat": 40.7019,
    "lon": -73.9736,
    "label": "H214"
   },
   {
    "lat": 40.7216,
    "lon": -73.96687,
    "label": "H215"
   },
   {
    "lat": 40.6507,
    "lon": -74.03188,
    "label": "H119"
   },
   {
    "lat": 40.77498,
    "lon": -73.93864,
    "label": "H091"
   },
   {
    "lat": 40.64678,
    "lon": -74.03411,
    "label": "H401"
   },
   {
    "lat": 40.70424,
    "lon": -73.99506,
    "label": "H120"
   },
   {
    "lat": 40.80539,
    "lon": -73.83704,
    "label": "H301"
   },
   {
    "lat": 40.74591,
    "lon": -73.96739,
    "label": "H501"
   }
  ],
  "asOf": "2026-07-24T11:13:45.092Z"
 },
 "cameras": {
  "total": 969,
  "list": [
   {
    "name": "Hutchhinson River Pkwy @ Westchester Ave",
    "url": "https://webcams.nyctmc.org/api/cameras/15fca74d-c3e9-42ee-8f32-5b708ef36477/image"
   },
   {
    "name": "7 Ave NB @ Bay Ridge Pkwy",
    "url": "https://webcams.nyctmc.org/api/cameras/7a830ac8-1cce-4a85-b3de-44d74900b9bc/image"
   },
   {
    "name": "Rockaway Blvd @ Van Wyck Expy E S/R",
    "url": "https://webcams.nyctmc.org/api/cameras/857e40b2-566a-4917-bc08-47920babf3f9/image"
   },
   {
    "name": "Canal Street @ Chrystie Street",
    "url": "https://webcams.nyctmc.org/api/cameras/8cc75cbc-e050-4947-aee8-639f63fe4ca7/image"
   },
   {
    "name": "C3-SIE-09-EB_at_ Manor_Rd",
    "url": "https://webcams.nyctmc.org/api/cameras/5ec4ce2f-d86d-4899-b464-436fdcde72eb/image"
   },
   {
    "name": "Bruckner Expy @ Wilkinson Ave",
    "url": "https://webcams.nyctmc.org/api/cameras/d24b0435-67e7-498a-91f6-f3a65bd86be2/image"
   },
   {
    "name": "C2-BQE-04_WB_at_Sackett_St-Ex26",
    "url": "https://webcams.nyctmc.org/api/cameras/1da7a29e-9993-4b93-b13a-e29b40c2069d/image"
   },
   {
    "name": "Rockaway Blvd @ Brookville Blvd",
    "url": "https://webcams.nyctmc.org/api/cameras/cb94f806-6014-496b-960b-9f747109980e/image"
   },
   {
    "name": "11 Ave @ 57 St",
    "url": "https://webcams.nyctmc.org/api/cameras/6024ac17-0c26-4435-96e5-560c41b920ad/image"
   },
   {
    "name": "West Shore Expy @ South Ave",
    "url": "https://webcams.nyctmc.org/api/cameras/a6b2c1c8-1124-4dec-aa22-c8d87f6835ec/image"
   },
   {
    "name": "C1-CBE-03_N_NB_at_Nelson_Ave-Ex02A",
    "url": "https://webcams.nyctmc.org/api/cameras/4302c1d7-48aa-45a8-a9cc-93e3132c1530/image"
   },
   {
    "name": "Flatbush Ave @ DeKalb Ave",
    "url": "https://webcams.nyctmc.org/api/cameras/243e945a-b872-4bac-9898-94ce8963ef44/image"
   },
   {
    "name": "Cross Bay Blvd @ 20 Rd",
    "url": "https://webcams.nyctmc.org/api/cameras/b995be5a-a469-4cf6-b2ee-197e8e9eecd9/image"
   },
   {
    "name": "Riverside Dr @ 79 St",
    "url": "https://webcams.nyctmc.org/api/cameras/36672d97-80d3-48f0-b3c4-6e6125069b90/image"
   },
   {
    "name": "Richmond Ave @ Wainwright Ave",
    "url": "https://webcams.nyctmc.org/api/cameras/a10cbaf4-ea20-4a01-93a3-b338cd92370b/image"
   },
   {
    "name": "Soundview Ave @ Lafayette Ave",
    "url": "https://webcams.nyctmc.org/api/cameras/894dd92a-90a3-46d5-a996-4ddb2b6091cc/image"
   },
   {
    "name": "BQE @ Sands St",
    "url": "https://webcams.nyctmc.org/api/cameras/8ea73365-6c7b-423a-87fc-4b6fc279dafa/image"
   },
   {
    "name": "Flushing Ave @ Fresh Pond Rd",
    "url": "https://webcams.nyctmc.org/api/cameras/b9085289-750b-403a-8031-681678d35ae0/image"
   }
  ],
  "asOf": "2026-07-24T11:13:45.747Z"
 },
 "floodnet": {
  "sensors": 388,
  "flooding": 0,
  "wettest": null,
  "wet": [],
  "asOf": "2026-07-24T11:02:24.000Z"
 },
 "coned": {
  "customersOut": 34,
  "customersServed": 3626606,
  "outages": 13,
  "asOf": "2026-07-24T11:05:00.000Z"
 },
 "path": {
  "arrivals": 55,
  "stations": 13,
  "asOf": "2026-07-24T11:15:23.452Z"
 },
 "reservoirs": {
  "pctFull": 87.3,
  "pctNormal": 91,
  "pageDate": null,
  "asOf": "2026-07-24T11:15:23.612Z"
 }
}