{
 "generated": "2026-07-19T19:54:41.276Z",
 "nyiso": {
  "nycLoadMw": 6601.227,
  "isoLoadMw": 17392.6154,
  "asOf": "2026-07-19T19:40:00.000Z",
  "fuelMix": [
   {
    "fuel": "Dual Fuel",
    "mw": 3922
   },
   {
    "fuel": "Natural Gas",
    "mw": 4013
   },
   {
    "fuel": "Nuclear",
    "mw": 3238
   },
   {
    "fuel": "Other Fossil Fuels",
    "mw": 0
   },
   {
    "fuel": "Other Renewables",
    "mw": 754
   },
   {
    "fuel": "Wind",
    "mw": 782
   },
   {
    "fuel": "Hydro",
    "mw": 2968
   }
  ],
  "fuelAsOf": "2026-07-19T19:35:00.000Z",
  "nycPriceMwh": 35.39,
  "priceAsOf": "2026-07-19T19:50:00.000Z"
 },
 "buoy": {
  "waveHeightM": 0.8,
  "domPeriodS": 8,
  "waterTempC": 23.3,
  "windMs": 4,
  "airTempC": 23.6,
  "pressureHpa": 1010.9,
  "asOf": "2026-07-19T19:20:00.000Z"
 },
 "subway": {
  "trains": 436,
  "feedsOk": 8,
  "feeds": 8,
  "alerts": 23,
  "asOf": "2026-07-19T19:54:42.468Z"
 },
 "rail": {
  "lirr": {
   "trains": 36,
   "viaVehicles": false
  },
  "mnr": {
   "trains": 191,
   "viaVehicles": true
  },
  "asOf": "2026-07-19T19:54:42.651Z"
 },
 "ferry": {
  "vessels": 30,
  "positions": [
   {
    "lat": 40.65549,
    "lon": -74.02441,
    "label": "H200"
   },
   {
    "lat": 40.70301,
    "lon": -74.00656,
    "label": "H201"
   },
   {
    "lat": 40.70864,
    "lon": -73.98641,
    "label": "H202"
   },
   {
    "lat": 40.66251,
    "lon": -74.02258,
    "label": "H101"
   },
   {
    "lat": 40.70698,
    "lon": -73.9856,
    "label": "H102"
   },
   {
    "lat": 40.69274,
    "lon": -74.00349,
    "label": "H103"
   },
   {
    "lat": 40.70316,
    "lon": -74.00671,
    "label": "H104"
   },
   {
    "lat": 40.70874,
    "lon": -73.97046,
    "label": "H105"
   },
   {
    "lat": 40.74437,
    "lon": -73.97033,
    "label": "H106"
   },
   {
    "lat": 40.74988,
    "lon": -74.01488,
    "label": "H107"
   },
   {
    "lat": 40.57544,
    "lon": -74.02058,
    "label": "H108"
   },
   {
    "lat": 40.70827,
    "lon": -73.98086,
    "label": "H109"
   },
   {
    "lat": 40.63997,
    "lon": -74.03796,
    "label": "H203"
   },
   {
    "lat": 40.71465,
    "lon": -74.01769,
    "label": "H204"
   },
   {
    "lat": 40.70543,
    "lon": -73.99287,
    "label": "H208"
   },
   {
    "lat": 40.58246,
    "lon": -73.83041,
    "label": "SB402"
   },
   {
    "lat": 40.70395,
    "lon": -73.97462,
    "label": "H114"
   },
   {
    "lat": 40.80409,
    "lon": -73.84897,
    "label": "H111"
   },
   {
    "lat": 40.57647,
    "lon": -73.8699,
    "label": "H115"
   },
   {
    "lat": 40.58413,
    "lon": -73.83188,
    "label": "H113"
   },
   {
    "lat": 40.65004,
    "lon": -74.03116,
    "label": "H090"
   },
   {
    "lat": 40.61099,
    "lon": -74.04375,
    "label": "H214"
   },
   {
    "lat": 40.74823,
    "lon": -73.95784,
    "label": "H215"
   },
   {
    "lat": 40.77146,
    "lon": -73.93601,
    "label": "H091"
   },
   {
    "lat": 40.77763,
    "lon": -73.94218,
    "label": "H401"
   },
   {
    "lat": 40.72087,
    "lon": -73.96509,
    "label": "H120"
   },
   {
    "lat": 40.68817,
    "lon": -74.0097,
    "label": "H301"
   },
   {
    "lat": 40.74326,
    "lon": -73.97104,
    "label": "H501"
   },
   {
    "lat": 40.69745,
    "lon": -74.00721,
    "label": "H121"
   },
   {
    "lat": 40.70252,
    "lon": -74.00755,
    "label": "H122"
   }
  ],
  "asOf": "2026-07-19T19:54:42.800Z"
 },
 "cameras": {
  "total": 956,
  "list": [
   {
    "name": "C1-MDE-11-NB_at_W.179th_St-Ex8",
    "url": "https://webcams.nyctmc.org/api/cameras/b9ba6a87-0e0b-4c5a-ad6a-7ead399e0864/image"
   },
   {
    "name": "Ocean Pkwy @ Ave X",
    "url": "https://webcams.nyctmc.org/api/cameras/64ed1f5d-ba90-4c12-afda-9a9c3e658efd/image"
   },
   {
    "name": "Cross Island Pkwy @ Union Tpke",
    "url": "https://webcams.nyctmc.org/api/cameras/7ae83f13-3d0e-4fd3-bc88-6fc41bde04c3/image"
   },
   {
    "name": "Houston St @ Broadway",
    "url": "https://webcams.nyctmc.org/api/cameras/5214cfe8-ccfc-42e9-8e2a-ff2865c1a518/image"
   },
   {
    "name": "SIE @ Clove Rd",
    "url": "https://webcams.nyctmc.org/api/cameras/2d1ed99a-c3d3-4616-a0d6-a9fe16f3e48c/image"
   },
   {
    "name": "Pelham Pkwy @ Stillwell Ave",
    "url": "https://webcams.nyctmc.org/api/cameras/6029af32-7e3c-412f-804e-b34166300799/image"
   },
   {
    "name": "C2-GE-02-WB_at_Ft_Hmiltn_Pkwy-Ex19",
    "url": "https://webcams.nyctmc.org/api/cameras/680f6950-8ae6-4746-b8ce-4bc28f10f79d/image"
   },
   {
    "name": "Springfield Ave @ Jamaica Ave",
    "url": "https://webcams.nyctmc.org/api/cameras/bf5db978-c464-44c9-ac88-af9977af4505/image"
   },
   {
    "name": "Central Park @ 72nd St Post 37",
    "url": "https://webcams.nyctmc.org/api/cameras/3f04a686-f97c-4187-8968-cb09265e08ff/image"
   },
   {
    "name": "Drumgoole Rd West @ Arthur Kill Rd  - ptz -141.58",
    "url": "https://webcams.nyctmc.org/api/cameras/8c4595b4-b1cd-4707-8fe8-3178c4ca93d1/image"
   },
   {
    "name": "C1-BRE-06_W - WB_at_CBX-Hutch_Int-EX6A",
    "url": "https://webcams.nyctmc.org/api/cameras/b221fdc4-ca81-41ae-875e-bf0341377758/image"
   },
   {
    "name": "BQE @ Sands St (eastbound) - video detection",
    "url": "https://webcams.nyctmc.org/api/cameras/68fc6239-198c-4d14-a408-0128d6bf0ace/image"
   },
   {
    "name": "C5-GCP-07-EB_at_Ditmars_Blvd-Ex9",
    "url": "https://webcams.nyctmc.org/api/cameras/d3503d31-e652-4618-9442-cf613600ea0b/image"
   },
   {
    "name": "Rockefeller Plaza @ W 51 St",
    "url": "https://webcams.nyctmc.org/api/cameras/bff9cee2-1513-4af3-9838-ea7a35552049/image"
   },
   {
    "name": "Lily Pond Ave @ School Rd",
    "url": "https://webcams.nyctmc.org/api/cameras/1c3a5c25-a40c-40d6-8f6b-030294269fd1/image"
   },
   {
    "name": "Henry Hudson Pkwy @ 232 St",
    "url": "https://webcams.nyctmc.org/api/cameras/97190ee9-e92c-46ef-a3fc-e8c75d416a9a/image"
   },
   {
    "name": "Wythe Ave @ Williamsburg st E",
    "url": "https://webcams.nyctmc.org/api/cameras/45b87983-6659-4be7-a354-15d756664204/image"
   },
   {
    "name": "QBB LL CM @ 11 St",
    "url": "https://webcams.nyctmc.org/api/cameras/282429c3-3f55-4fa6-bca2-b128262699d4/image"
   }
  ],
  "asOf": "2026-07-19T19:54:43.308Z"
 },
 "floodnet": {
  "sensors": 374,
  "flooding": 0,
  "wettest": null,
  "wet": [],
  "asOf": "2026-07-19T19:55:12.000Z"
 },
 "coned": {
  "customersOut": 269,
  "customersServed": 3626606,
  "outages": 42,
  "asOf": "2026-07-19T19:50:00.000Z"
 },
 "path": {
  "arrivals": 53,
  "stations": 13,
  "asOf": "2026-07-19T19:56:18.362Z"
 },
 "reservoirs": {
  "pctFull": 87.8,
  "pctNormal": 92.7,
  "pageDate": "July 17, 2026",
  "asOf": "2026-07-19T19:56:18.750Z"
 }
}