{
 "generated": "2026-07-23T03:23:03.468Z",
 "nyiso": {
  "nycLoadMw": 6756.592,
  "isoLoadMw": 19067.3335,
  "asOf": "2026-07-23T03:10:00.000Z",
  "fuelMix": [
   {
    "fuel": "Dual Fuel",
    "mw": 4927
   },
   {
    "fuel": "Natural Gas",
    "mw": 4544
   },
   {
    "fuel": "Nuclear",
    "mw": 3237
   },
   {
    "fuel": "Other Fossil Fuels",
    "mw": 0
   },
   {
    "fuel": "Other Renewables",
    "mw": 222
   },
   {
    "fuel": "Wind",
    "mw": 791
   },
   {
    "fuel": "Hydro",
    "mw": 2421
   }
  ],
  "fuelAsOf": "2026-07-23T03:05:00.000Z",
  "nycPriceMwh": 52.8,
  "priceAsOf": "2026-07-23T03:20:00.000Z"
 },
 "buoy": {
  "waveHeightM": 1.4,
  "domPeriodS": 9,
  "waterTempC": 23.6,
  "windMs": 5,
  "airTempC": 24.6,
  "pressureHpa": 1013.1,
  "asOf": "2026-07-23T02:50:00.000Z"
 },
 "subway": {
  "trains": 311,
  "feedsOk": 8,
  "feeds": 8,
  "alerts": 12,
  "asOf": "2026-07-23T03:23:04.554Z"
 },
 "rail": {
  "lirr": {
   "trains": 39,
   "viaVehicles": true
  },
  "mnr": {
   "trains": 102,
   "viaVehicles": true
  },
  "asOf": "2026-07-23T03:23:04.644Z"
 },
 "ferry": {
  "vessels": 0,
  "positions": [],
  "asOf": "2026-07-23T03:23:04.702Z"
 },
 "cameras": {
  "total": 969,
  "list": [
   {
    "name": "C1-BRE-10-NB_at_Middle_Twn_Rd-Ex7C",
    "url": "https://webcams.nyctmc.org/api/cameras/e38e3af7-19e6-4c8d-aa05-a21c8d5a7b29/image"
   },
   {
    "name": "7 Ave @ 18 St",
    "url": "https://webcams.nyctmc.org/api/cameras/40961631-fb83-4f48-8ffb-3385448d4e5f/image"
   },
   {
    "name": "College Point Blvd @ 35 Ave",
    "url": "https://webcams.nyctmc.org/api/cameras/279720e5-7db3-4143-9608-531cfc50dc25/image"
   },
   {
    "name": "Broadway @ 169 Street",
    "url": "https://webcams.nyctmc.org/api/cameras/d7910856-9d2c-4142-b8cc-cbd6c4b3acac/image"
   },
   {
    "name": "SIE @ Richmond Ave",
    "url": "https://webcams.nyctmc.org/api/cameras/1389ca99-0d3f-4c27-bc45-b0aa238ea7d2/image"
   },
   {
    "name": "Grand Concourse @ E 149 St",
    "url": "https://webcams.nyctmc.org/api/cameras/62380b5a-8960-4c2b-9125-d7f088605a7f/image"
   },
   {
    "name": "Belt Pkwy @ Ocean Pkwy",
    "url": "https://webcams.nyctmc.org/api/cameras/9bdd7740-762f-48e9-b40c-3db03c2a43f5/image"
   },
   {
    "name": "LIE @ College Point Blvd",
    "url": "https://webcams.nyctmc.org/api/cameras/6ab24015-2446-4410-b7a4-d8dd13ed2f8b/image"
   },
   {
    "name": "12 Ave @ 42 St",
    "url": "https://webcams.nyctmc.org/api/cameras/9bd74b87-32d1-4767-8081-86a2e83f28f2/image"
   },
   {
    "name": "Staten Island Expy @ Hylan Blvd",
    "url": "https://webcams.nyctmc.org/api/cameras/0b7a91d5-e33e-42b3-a05a-951be0ab1663/image"
   },
   {
    "name": "Webster Ave @ E 180 St",
    "url": "https://webcams.nyctmc.org/api/cameras/e08c24be-e2fe-4d83-bc08-bf88cdebdd63/image"
   },
   {
    "name": "Prospect Pkwy @ 3 Ave",
    "url": "https://webcams.nyctmc.org/api/cameras/91c033b3-ecfd-4fb9-b27d-d256eb720789/image"
   },
   {
    "name": "C5-BQE-37-EB_at_41st_Ave",
    "url": "https://webcams.nyctmc.org/api/cameras/b5b12361-b5b6-483f-a76e-b6cf98e06694/image"
   },
   {
    "name": "FDR Dr @ Catherine Street",
    "url": "https://webcams.nyctmc.org/api/cameras/beda95e2-f7d1-43a3-9a8b-7ab89e03f296/image"
   },
   {
    "name": "Lily Pond Ave @ School Rd",
    "url": "https://webcams.nyctmc.org/api/cameras/1c3a5c25-a40c-40d6-8f6b-030294269fd1/image"
   },
   {
    "name": "C1-CBX-18-Med_at_Pennyfield_Av-TNB",
    "url": "https://webcams.nyctmc.org/api/cameras/e51a2974-8ca2-4fe2-a90a-842685cbbcc9/image"
   },
   {
    "name": "3 Ave @ 65 St - Ent. EB BQE/Gowanus",
    "url": "https://webcams.nyctmc.org/api/cameras/be6b6830-b90d-40ab-98ab-9d67eb81e673/image"
   },
   {
    "name": "Astoria Blvd N S/R @ 32 St",
    "url": "https://webcams.nyctmc.org/api/cameras/cbd7c7a6-9bc5-4d6d-baf4-61b648dd589d/image"
   }
  ],
  "asOf": "2026-07-23T03:23:04.963Z"
 },
 "floodnet": {
  "sensors": 389,
  "flooding": 0,
  "wettest": null,
  "wet": [],
  "asOf": "2026-07-23T03:21:36.000Z"
 },
 "coned": {
  "customersOut": 641,
  "customersServed": 3626606,
  "outages": 34,
  "asOf": "2026-07-23T03:20:00.000Z"
 },
 "path": {
  "arrivals": 28,
  "stations": 13,
  "asOf": "2026-07-23T03:24:37.418Z"
 },
 "reservoirs": {
  "pctFull": 87.3,
  "pctNormal": 91.2,
  "pageDate": "July 22, 2026",
  "asOf": "2026-07-23T03:24:37.521Z"
 }
}