{
 "generated": "2026-07-19T21:17:51.585Z",
 "nyiso": {
  "nycLoadMw": 6771.7383,
  "isoLoadMw": 18675.0911,
  "asOf": "2026-07-19T21:00:00.000Z",
  "fuelMix": [
   {
    "fuel": "Dual Fuel",
    "mw": 4905
   },
   {
    "fuel": "Natural Gas",
    "mw": 4479
   },
   {
    "fuel": "Nuclear",
    "mw": 3231
   },
   {
    "fuel": "Other Fossil Fuels",
    "mw": 5
   },
   {
    "fuel": "Other Renewables",
    "mw": 688
   },
   {
    "fuel": "Wind",
    "mw": 663
   },
   {
    "fuel": "Hydro",
    "mw": 3075
   }
  ],
  "fuelAsOf": "2026-07-19T21:00:00.000Z",
  "nycPriceMwh": 38.15,
  "priceAsOf": "2026-07-19T21:15:00.000Z"
 },
 "buoy": {
  "waveHeightM": 0.9,
  "domPeriodS": 8,
  "waterTempC": 23.4,
  "windMs": 4,
  "airTempC": 24,
  "pressureHpa": 1010.6,
  "asOf": "2026-07-19T20:50:00.000Z"
 },
 "subway": {
  "trains": 427,
  "feedsOk": 8,
  "feeds": 8,
  "alerts": 24,
  "asOf": "2026-07-19T21:17:53.012Z"
 },
 "rail": {
  "lirr": {
   "trains": 36,
   "viaVehicles": false
  },
  "mnr": {
   "trains": 190,
   "viaVehicles": true
  },
  "asOf": "2026-07-19T21:17:53.248Z"
 },
 "ferry": {
  "vessels": 30,
  "positions": [
   {
    "lat": 40.7241,
    "lon": -74.02527,
    "label": "H200"
   },
   {
    "lat": 40.70313,
    "lon": -74.0067,
    "label": "H201"
   },
   {
    "lat": 40.65566,
    "lon": -74.02586,
    "label": "H202"
   },
   {
    "lat": 40.70253,
    "lon": -74.00427,
    "label": "H101"
   },
   {
    "lat": 40.64001,
    "lon": -74.03817,
    "label": "H102"
   },
   {
    "lat": 40.76038,
    "lon": -74.00425,
    "label": "H103"
   },
   {
    "lat": 40.70613,
    "lon": -73.9921,
    "label": "H104"
   },
   {
    "lat": 40.74439,
    "lon": -73.97063,
    "label": "H105"
   },
   {
    "lat": 40.77021,
    "lon": -73.93756,
    "label": "H106"
   },
   {
    "lat": 40.6923,
    "lon": -74.00229,
    "label": "H107"
   },
   {
    "lat": 40.77905,
    "lon": -73.93598,
    "label": "H108"
   },
   {
    "lat": 40.79861,
    "lon": -73.87891,
    "label": "H109"
   },
   {
    "lat": 40.72941,
    "lon": -73.966,
    "label": "H203"
   },
   {
    "lat": 40.6462,
    "lon": -74.07417,
    "label": "H204"
   },
   {
    "lat": 40.70499,
    "lon": -73.99539,
    "label": "H208"
   },
   {
    "lat": 40.59828,
    "lon": -73.76646,
    "label": "SB402"
   },
   {
    "lat": 40.74456,
    "lon": -73.97015,
    "label": "H114"
   },
   {
    "lat": 40.70412,
    "lon": -74.00094,
    "label": "H111"
   },
   {
    "lat": 40.69872,
    "lon": -74.00508,
    "label": "H115"
   },
   {
    "lat": 40.67218,
    "lon": -74.02171,
    "label": "H113"
   },
   {
    "lat": 40.58399,
    "lon": -73.8332,
    "label": "H090"
   },
   {
    "lat": 40.61872,
    "lon": -74.04494,
    "label": "H214"
   },
   {
    "lat": 40.58429,
    "lon": -73.83134,
    "label": "H215"
   },
   {
    "lat": 40.70198,
    "lon": -73.9739,
    "label": "H091"
   },
   {
    "lat": 40.56515,
    "lon": -73.98447,
    "label": "H401"
   },
   {
    "lat": 40.70654,
    "lon": -73.97995,
    "label": "H120"
   },
   {
    "lat": 40.57225,
    "lon": -73.89352,
    "label": "H301"
   },
   {
    "lat": 40.73709,
    "lon": -73.96368,
    "label": "H501"
   },
   {
    "lat": 40.68679,
    "lon": -74.01635,
    "label": "H121"
   },
   {
    "lat": 40.71096,
    "lon": -73.97118,
    "label": "H122"
   }
  ],
  "asOf": "2026-07-19T21:17:53.386Z"
 },
 "cameras": {
  "total": 956,
  "list": [
   {
    "name": "Bruckner Blvd E @ Castle Hill Ave",
    "url": "https://webcams.nyctmc.org/api/cameras/420a58c7-3b5b-4a20-9f8d-d722d03f19ca/image"
   },
   {
    "name": "Flatbush Ave @ Empire Blvd",
    "url": "https://webcams.nyctmc.org/api/cameras/2e43a9d0-1df8-4a38-ae20-2e0f359bb55d/image"
   },
   {
    "name": "Woodhaven Blvd @ 101 Ave",
    "url": "https://webcams.nyctmc.org/api/cameras/e6c39111-6d28-45bb-9698-509699e78b8f/image"
   },
   {
    "name": "Broadway @ Vesey St",
    "url": "https://webcams.nyctmc.org/api/cameras/73b66e92-508f-407c-bada-883ab992fde0/image"
   },
   {
    "name": "West Shore Expy @ Arden Ave",
    "url": "https://webcams.nyctmc.org/api/cameras/23cb2c44-1a40-4950-a914-ee7f1390553c/image"
   },
   {
    "name": "C1-BRE-06_W - WB_at_CBX-Hutch_Int-EX6A",
    "url": "https://webcams.nyctmc.org/api/cameras/b221fdc4-ca81-41ae-875e-bf0341377758/image"
   },
   {
    "name": "Metropolitan Ave @ Marcy Ave",
    "url": "https://webcams.nyctmc.org/api/cameras/0ed1503d-23fc-4102-ada3-5d647a7b20cb/image"
   },
   {
    "name": "QBB UL @ Queens Pier",
    "url": "https://webcams.nyctmc.org/api/cameras/bfcb2b32-7ae7-4060-a39b-80f71a1db289/image"
   },
   {
    "name": "FDR Dr @ 90 St",
    "url": "https://webcams.nyctmc.org/api/cameras/874223a4-dc80-4764-8d91-1590cd3737d4/image"
   },
   {
    "name": "Drumgoogle Rd E @ Vernon Ave",
    "url": "https://webcams.nyctmc.org/api/cameras/29aaea67-bf67-4d6f-b572-f810f48f5b48/image"
   },
   {
    "name": "Hutchhinson River Pkwy @ Waterbury Ave",
    "url": "https://webcams.nyctmc.org/api/cameras/bfeb2434-fd55-4024-8172-f9602ea6ae06/image"
   },
   {
    "name": "Cadman Plz West @ Tillary St",
    "url": "https://webcams.nyctmc.org/api/cameras/07c5a9ab-38b0-4176-a932-395cded5858e/image"
   },
   {
    "name": "Northern Blvd @ 48 St",
    "url": "https://webcams.nyctmc.org/api/cameras/10a4be9a-8a1e-4b0c-84c3-b51c887b5e27/image"
   },
   {
    "name": "Ave of Americas @ Central Park South",
    "url": "https://webcams.nyctmc.org/api/cameras/332f161d-47cb-4c8a-b6b6-5ad48a55c978/image"
   },
   {
    "name": "Victory Blvd @ Loop Rd -131.42",
    "url": "https://webcams.nyctmc.org/api/cameras/7add8765-182d-40e5-b196-a0e3c02ed787/image"
   },
   {
    "name": "Bruckner Blvd @ Lincoln Ave",
    "url": "https://webcams.nyctmc.org/api/cameras/82b0f566-cab5-4366-bc3a-67f82cc4fec7/image"
   },
   {
    "name": "BB-26 South Rdwy @ West of Manhattan Twr",
    "url": "https://webcams.nyctmc.org/api/cameras/3fd80992-482b-4e88-ad7f-8c74690a8d37/image"
   },
   {
    "name": "Queens Plaza North @ 2811 (Westside)",
    "url": "https://webcams.nyctmc.org/api/cameras/76ce9adc-f73d-46b7-9ca7-fe6d7521b603/image"
   }
  ],
  "asOf": "2026-07-19T21:17:53.910Z"
 },
 "floodnet": {
  "sensors": 374,
  "flooding": 0,
  "wettest": null,
  "wet": [],
  "asOf": "2026-07-19T21:07:12.000Z"
 },
 "coned": {
  "customersOut": 130,
  "customersServed": 3626606,
  "outages": 36,
  "asOf": "2026-07-19T21:05:00.000Z"
 },
 "path": {
  "arrivals": 53,
  "stations": 13,
  "asOf": "2026-07-19T21:19:24.178Z"
 },
 "reservoirs": {
  "pctFull": 87.8,
  "pctNormal": 92.7,
  "pageDate": "July 17, 2026",
  "asOf": "2026-07-19T21:19:24.640Z"
 }
}