{
 "generated": "2026-07-19T17:22:30.285Z",
 "nyiso": {
  "nycLoadMw": 6260.874,
  "isoLoadMw": 15839.6548,
  "asOf": "2026-07-19T17:05:00.000Z",
  "fuelMix": [
   {
    "fuel": "Dual Fuel",
    "mw": 3346
   },
   {
    "fuel": "Natural Gas",
    "mw": 3285
   },
   {
    "fuel": "Nuclear",
    "mw": 3241
   },
   {
    "fuel": "Other Fossil Fuels",
    "mw": 0
   },
   {
    "fuel": "Other Renewables",
    "mw": 753
   },
   {
    "fuel": "Wind",
    "mw": 716
   },
   {
    "fuel": "Hydro",
    "mw": 2850
   }
  ],
  "fuelAsOf": "2026-07-19T17:05:00.000Z"
 },
 "buoy": {
  "waveHeightM": 0.8,
  "domPeriodS": 4,
  "waterTempC": 23.1,
  "windMs": 9,
  "airTempC": 23.3,
  "pressureHpa": 1010.5,
  "asOf": "2026-07-19T16:50:00.000Z"
 },
 "subway": {
  "trains": 414,
  "feedsOk": 8,
  "feeds": 8,
  "alerts": 23,
  "asOf": "2026-07-19T17:22:31.915Z"
 },
 "rail": {
  "lirr": {
   "trains": 36,
   "viaVehicles": false
  },
  "mnr": {
   "trains": 202,
   "viaVehicles": true
  },
  "asOf": "2026-07-19T17:22:32.407Z"
 },
 "ferry": {
  "vessels": 30,
  "positions": [
   {
    "lat": 40.64833,
    "lon": -74.03349,
    "label": "H200"
   },
   {
    "lat": 40.74439,
    "lon": -73.9706,
    "label": "H201"
   },
   {
    "lat": 40.74195,
    "lon": -73.97054,
    "label": "H202"
   },
   {
    "lat": 40.69648,
    "lon": -74.00364,
    "label": "H101"
   },
   {
    "lat": 40.69231,
    "lon": -74.00226,
    "label": "H102"
   },
   {
    "lat": 40.64093,
    "lon": -74.03798,
    "label": "H103"
   },
   {
    "lat": 40.745,
    "lon": -73.96922,
    "label": "H104"
   },
   {
    "lat": 40.70464,
    "lon": -73.99453,
    "label": "H105"
   },
   {
    "lat": 40.77784,
    "lon": -73.94167,
    "label": "H106"
   },
   {
    "lat": 40.71538,
    "lon": -74.01781,
    "label": "H107"
   },
   {
    "lat": 40.77767,
    "lon": -73.94217,
    "label": "H108"
   },
   {
    "lat": 40.70335,
    "lon": -74.00532,
    "label": "H109"
   },
   {
    "lat": 40.63998,
    "lon": -74.03796,
    "label": "H203"
   },
   {
    "lat": 40.73296,
    "lon": -74.01749,
    "label": "H204"
   },
   {
    "lat": 40.73334,
    "lon": -73.96729,
    "label": "H208"
   },
   {
    "lat": 40.59578,
    "lon": -73.7747,
    "label": "SB402"
   },
   {
    "lat": 40.70481,
    "lon": -73.97526,
    "label": "H114"
   },
   {
    "lat": 40.58326,
    "lon": -73.85456,
    "label": "H111"
   },
   {
    "lat": 40.80379,
    "lon": -73.84962,
    "label": "H115"
   },
   {
    "lat": 40.58416,
    "lon": -73.83185,
    "label": "H113"
   },
   {
    "lat": 40.64648,
    "lon": -74.02687,
    "label": "H090"
   },
   {
    "lat": 40.62768,
    "lon": -74.04593,
    "label": "H214"
   },
   {
    "lat": 40.5655,
    "lon": -73.97099,
    "label": "H215"
   },
   {
    "lat": 40.70639,
    "lon": -73.97589,
    "label": "H091"
   },
   {
    "lat": 40.5644,
    "lon": -73.95609,
    "label": "H401"
   },
   {
    "lat": 40.70383,
    "lon": -73.99564,
    "label": "H120"
   },
   {
    "lat": 40.70941,
    "lon": -73.97623,
    "label": "H301"
   },
   {
    "lat": 40.70313,
    "lon": -74.0067,
    "label": "H501"
   },
   {
    "lat": 40.69166,
    "lon": -74.009,
    "label": "H121"
   },
   {
    "lat": 40.72566,
    "lon": -73.96519,
    "label": "H122"
   }
  ],
  "asOf": "2026-07-19T17:22:32.584Z"
 },
 "cameras": {
  "total": 957,
  "list": [
   {
    "name": "C1-CBE-06_N_NB_at_Weeks Ave-Ext02B",
    "url": "https://webcams.nyctmc.org/api/cameras/4d85c576-4313-4562-8eb5-0d9773ea2bf1/image"
   },
   {
    "name": "Old Fulton @ Vine St @ Hicks St",
    "url": "https://webcams.nyctmc.org/api/cameras/4d84b5d0-c9da-4916-8b0d-4f3d573d3509/image"
   },
   {
    "name": "Grand Ave @ Hamilton Pl",
    "url": "https://webcams.nyctmc.org/api/cameras/b08600e6-7189-4104-a484-709dc81a3fa7/image"
   },
   {
    "name": "6 Ave @ 30 St",
    "url": "https://webcams.nyctmc.org/api/cameras/0dc7c2b4-614d-46a3-9610-3ba09f3f1284/image"
   },
   {
    "name": "C3-SIE-15-EB_at_Fingerboard_Rd_Ex15",
    "url": "https://webcams.nyctmc.org/api/cameras/261853c1-91c6-4007-9d52-ed530d1a826a/image"
   },
   {
    "name": "C1-SHE-02-SB_at_Cross_Brx_Expwy",
    "url": "https://webcams.nyctmc.org/api/cameras/d67b0c15-549a-42f9-b99c-13023667f724/image"
   },
   {
    "name": "C2-BQE-20-WB_at_Wythe_Ave-Ex31",
    "url": "https://webcams.nyctmc.org/api/cameras/6d42b7fb-604b-4172-b35d-c0556c5d3fcf/image"
   },
   {
    "name": "Qns Blvd @ QnCnt Mall",
    "url": "https://webcams.nyctmc.org/api/cameras/52f3d48e-3bb4-4c83-bec2-1fb664d56501/image"
   },
   {
    "name": "FDR @ E 6 St",
    "url": "https://webcams.nyctmc.org/api/cameras/c75873dc-16d0-4e9c-b5b5-1c6ede0b0b63/image"
   },
   {
    "name": "C3-SIE-11-EB_at_Renwick_Ave",
    "url": "https://webcams.nyctmc.org/api/cameras/bcb706e6-135a-4981-8a06-7545f6e05ddd/image"
   },
   {
    "name": "New Eng Thru @ Bartow",
    "url": "https://webcams.nyctmc.org/api/cameras/4f806706-c888-4926-932c-f9f3f0255b60/image"
   },
   {
    "name": "Smith St @ 9 St - 170.106",
    "url": "https://webcams.nyctmc.org/api/cameras/d766db98-8b2c-406a-b0ea-f437e2216157/image"
   },
   {
    "name": "Northern Blvd @ 82 St",
    "url": "https://webcams.nyctmc.org/api/cameras/08c40d18-cacf-4139-aa64-ba8f8602af53/image"
   },
   {
    "name": "9 Ave @ 45 St",
    "url": "https://webcams.nyctmc.org/api/cameras/f865d9bf-0062-4d43-9c16-2a862d8af4f0/image"
   },
   {
    "name": "West Shore Expy @ Rossville Ave",
    "url": "https://webcams.nyctmc.org/api/cameras/4bb3c648-45f8-4134-9ac8-fb56f2f851fa/image"
   },
   {
    "name": "Fordham Rd @ Major Deegan Expy",
    "url": "https://webcams.nyctmc.org/api/cameras/b591a4be-a1aa-4978-ab2c-be4a17eb190e/image"
   },
   {
    "name": "Linden Blvd @ Pennsylvania Ave",
    "url": "https://webcams.nyctmc.org/api/cameras/a8389158-7e9c-4e57-8127-841f710582f8/image"
   },
   {
    "name": "Clearview Expy @ 35 St",
    "url": "https://webcams.nyctmc.org/api/cameras/247c548c-da8e-45fc-8183-6f82be28edee/image"
   }
  ],
  "asOf": "2026-07-19T17:22:33.476Z"
 },
 "floodnet": {
  "sensors": 373,
  "flooding": 0,
  "wettest": null,
  "wet": [],
  "asOf": "2026-07-19T17:16:48.000Z"
 }
}